{"a11ywatch_cli/0.8.20/aarch64-apple-darwin":1,"a11ywatch_cli/0.8.20/x86_64-apple-darwin":1,"aocf/0.1.18/x86_64-unknown-linux-gnu":1,"aocf/0.1.18/x86_64-unknown-linux-musl":1,"aocf_cli/0.1.18/x86_64-unknown-linux-gnu":1,"aocf_cli/0.1.18/x86_64-unknown-linux-musl":1,"atuin/12.0.0/x86_64-unknown-linux-gnu":1,"atuin/12.0.0/x86_64-unknown-linux-musl":1,"bacon/2.2.6/aarch64-apple-darwin":1,"bacon/2.2.6/x86_64-apple-darwin":2,"bacon/2.2.7/aarch64-apple-darwin":1,"bacon/2.2.7/x86_64-apple-darwin":1,"bacon/2.2.7/x86_64-unknown-linux-gnu":1,"bacon/2.2.7/x86_64-unknown-linux-musl":1,"bat/0.22.1/x86_64-unknown-linux-gnu":2,"bat/0.22.1/x86_64-unknown-linux-musl":2,"binstall/0.1.0/x86_64-unknown-linux-gnu":2,"broot/1.17.0/x86_64-unknown-linux-gnu":2,"broot/1.17.0/x86_64-unknown-linux-musl":2,"bunny-api/0.0.5/x86_64-unknown-linux-musl":1,"cargo-about/0.5.2/x86_64-unknown-linux-gnu":2,"cargo-about/0.5.2/x86_64-unknown-linux-musl":2,"cargo-all-features/1.7.0/x86_64-unknown-linux-gnu":4,"cargo-all-features/1.7.0/x86_64-unknown-linux-musl":4,"cargo-apk/0.9.7/x86_64-pc-windows-msvc":1,"cargo-audit/0.17.4/x86_64-apple-darwin":1,"cargo-audit/0.17.4/x86_64-unknown-linux-gnu":42,"cargo-binstall/0.18.0/x86_64-apple-darwin":1,"cargo-binstall/0.18.1/aarch64-apple-darwin":14,"cargo-binstall/0.18.1/aarch64-unknown-linux-gnu":1,"cargo-binstall/0.18.1/armv7-unknown-linux-gnueabihf":2,"cargo-binstall/0.18.1/armv7-unknown-linux-musleabihf":1,"cargo-binstall/0.18.1/x86_64-apple-darwin":102,"cargo-binstall/0.18.1/x86_64-pc-windows-msvc":18,"cargo-binstall/0.18.1/x86_64-unknown-linux-gnu":153,"cargo-binstall/0.18.1/x86_64-unknown-linux-musl":148,"cargo-cache/0.8.3/x86_64-unknown-linux-gnu":1,"cargo-cache/0.8.3/x86_64-unknown-linux-musl":1,"cargo-chef/0.1.46/aarch64-unknown-linux-gnu":1,"cargo-chef/0.1.46/aarch64-unknown-linux-musl":1,"cargo-chef/0.1.46/x86_64-unknown-linux-gnu":12,"cargo-chef/0.1.46/x86_64-unknown-linux-musl":12,"cargo-chef/0.1.48/x86_64-unknown-linux-gnu":2,"cargo-chef/0.1.48/x86_64-unknown-linux-musl":2,"cargo-chef/0.1.49/x86_64-unknown-linux-gnu":2,"cargo-chef/0.1.49/x86_64-unknown-linux-musl":2,"cargo-chef/0.1.50/aarch64-unknown-linux-gnu":1,"cargo-chef/0.1.50/armv7-unknown-linux-gnueabihf":1,"cargo-chef/0.1.50/x86_64-apple-darwin":1,"cargo-chef/0.1.50/x86_64-unknown-linux-gnu":2,"cargo-chef/0.1.50/x86_64-unknown-linux-musl":1,"cargo-deb/1.41.0/x86_64-unknown-linux-gnu":5,"cargo-deb/1.41.0/x86_64-unknown-linux-musl":4,"cargo-deny/0.13.5/x86_64-apple-darwin":1,"cargo-deny/0.13.5/x86_64-unknown-linux-gnu":45,"cargo-deny/0.13.5/x86_64-unknown-linux-musl":8,"cargo-edit/0.11.6/x86_64-unknown-linux-gnu":9,"cargo-edit/0.11.6/x86_64-unknown-linux-musl":5,"cargo-fuzz/0.11.1/x86_64-apple-darwin":1,"cargo-generate/0.17.3/x86_64-unknown-linux-gnu":2,"cargo-generate/0.17.3/x86_64-unknown-linux-musl":2,"cargo-generate/0.17.4/aarch64-apple-darwin":1,"cargo-generate/0.17.4/x86_64-apple-darwin":1,"cargo-generate/0.17.4/x86_64-unknown-linux-gnu":1,"cargo-generate/0.17.4/x86_64-unknown-linux-musl":1,"cargo-hack/0.5.15/x86_64-unknown-linux-gnu":104,"cargo-license/0.5.1/x86_64-unknown-linux-musl":1,"cargo-llvm-cov/0.4.6/x86_64-unknown-linux-gnu":2,"cargo-llvm-cov/0.4.6/x86_64-unknown-linux-musl":2,"cargo-llvm-cov/0.5.0/x86_64-unknown-linux-gnu":25,"cargo-llvm-cov/0.5.2/x86_64-apple-darwin":1,"cargo-llvm-cov/0.5.2/x86_64-unknown-linux-gnu":8,"cargo-machete/0.5.0/x86_64-unknown-linux-gnu":1,"cargo-machete/0.5.0/x86_64-unknown-linux-musl":1,"cargo-make/0.35.15/x86_64-unknown-linux-gnu":198,"cargo-make/0.36.3/x86_64-unknown-linux-gnu":6,"cargo-make/0.36.3/x86_64-unknown-linux-musl":5,"cargo-modules/0.7.1/x86_64-unknown-linux-gnu":1,"cargo-modules/0.7.1/x86_64-unknown-linux-musl":1,"cargo-msrv/0.15.1/x86_64-unknown-linux-gnu":6,"cargo-msrv/0.15.1/x86_64-unknown-linux-musl":6,"cargo-nextest/0.9.28/x86_64-unknown-linux-gnu":103,"cargo-nextest/0.9.47/aarch64-unknown-linux-gnu":4,"cargo-nextest/0.9.47/aarch64-unknown-linux-musl":4,"cargo-nextest/0.9.47/x86_64-apple-darwin":1,"cargo-nextest/0.9.47/x86_64-pc-windows-msvc":1,"cargo-nextest/0.9.47/x86_64-unknown-linux-gnu":50,"cargo-nextest/0.9.47/x86_64-unknown-linux-musl":50,"cargo-outdated/0.11.1/x86_64-unknown-linux-gnu":1,"cargo-outdated/0.11.1/x86_64-unknown-linux-musl":1,"cargo-pants/0.4.7/x86_64-unknown-linux-gnu":7,"cargo-pants/0.4.7/x86_64-unknown-linux-musl":7,"cargo-quickinstall/0.2.6/x86_64-unknown-linux-gnu":12,"cargo-quickinstall/0.2.6/x86_64-unknown-linux-musl":12,"cargo-release/0.24.1/aarch64-apple-darwin":2,"cargo-release/0.24.1/x86_64-apple-darwin":3,"cargo-release/0.24.1/x86_64-unknown-linux-gnu":4,"cargo-release/0.24.1/x86_64-unknown-linux-musl":4,"cargo-semver-checks/0.14.0/x86_64-unknown-linux-gnu":3,"cargo-semver-checks/0.14.0/x86_64-unknown-linux-musl":3,"cargo-show-asm/0.2.7/x86_64-unknown-linux-gnu":1,"cargo-show-asm/0.2.7/x86_64-unknown-linux-musl":1,"cargo-sort/1.0.9/x86_64-unknown-linux-gnu":4,"cargo-spellcheck/0.12.3/x86_64-unknown-linux-gnu":37,"cargo-sweep/0.6.2/x86_64-unknown-linux-gnu":1,"cargo-sweep/0.6.2/x86_64-unknown-linux-musl":1,"cargo-sync-rdme/0.2.0/x86_64-apple-darwin":1,"cargo-sync-rdme/0.2.0/x86_64-pc-windows-msvc":1,"cargo-sync-rdme/0.2.0/x86_64-unknown-linux-gnu":4,"cargo-sync-rdme/0.2.0/x86_64-unknown-linux-musl":4,"cargo-tarpaulin/0.23.1/x86_64-unknown-linux-gnu":13,"cargo-tarpaulin/0.23.1/x86_64-unknown-linux-musl":9,"cargo-todo/0.2.1/x86_64-apple-darwin":1,"cargo-udeps/0.1.35/x86_64-unknown-linux-gnu":37,"cargo-unused-features/0.1.7/aarch64-apple-darwin":1,"cargo-unused-features/0.1.7/x86_64-apple-darwin":1,"cargo-update/11.1.1/aarch64-apple-darwin":1,"cargo-update/11.1.1/x86_64-apple-darwin":1,"cargo-update/11.1.1/x86_64-pc-windows-msvc":1,"cargo-update/11.1.1/x86_64-unknown-linux-gnu":4,"cargo-update/11.1.1/x86_64-unknown-linux-musl":4,"cargo-watch/8.1.1/x86_64-unknown-linux-gnu":24,"cargo-watch/8.1.1/x86_64-unknown-linux-musl":22,"cargo-watch/8.1.2/aarch64-unknown-linux-gnu":9,"cargo-watch/8.1.2/aarch64-unknown-linux-musl":9,"cargo-watch/8.1.2/armv7-unknown-linux-gnueabihf":1,"cargo-watch/8.1.2/x86_64-apple-darwin":24,"cargo-watch/8.1.2/x86_64-pc-windows-msvc":19,"cargo-watch/8.1.2/x86_64-unknown-linux-gnu":226,"cargo-watch/8.1.2/x86_64-unknown-linux-musl":218,"cargo-zigbuild/0.14.2/x86_64-unknown-linux-gnu":1,"cargo2junit/0.1.12/x86_64-unknown-linux-gnu":2,"clippy-sarif/0.3.4/x86_64-unknown-linux-gnu":5,"clippy-sarif/0.3.4/x86_64-unknown-linux-musl":5,"cocogitto/5.2.0/x86_64-unknown-linux-musl":24,"create-tauri-app/2.7.2/x86_64-pc-windows-msvc":1,"critcmp/0.1.7/x86_64-unknown-linux-gnu":10,"critcmp/0.1.7/x86_64-unknown-linux-musl":10,"cross/0.2.4/x86_64-unknown-linux-gnu":9,"cross/0.2.4/x86_64-unknown-linux-musl":9,"difftastic/0.38.0/x86_64-unknown-linux-gnu":1,"difftastic/0.38.0/x86_64-unknown-linux-musl":1,"dprint/0.33.0/x86_64-unknown-linux-gnu":2,"dprint/0.33.0/x86_64-unknown-linux-musl":2,"dua-cli/2.19.0/aarch64-apple-darwin":1,"dua-cli/2.19.0/x86_64-apple-darwin":1,"dua-cli/2.19.0/x86_64-unknown-linux-gnu":3,"dua-cli/2.19.0/x86_64-unknown-linux-musl":3,"els/0.1.11/x86_64-pc-windows-msvc":1,"fd-find/8.6.0/x86_64-unknown-linux-gnu":4,"fd-find/8.6.0/x86_64-unknown-linux-musl":3,"flamegraph/0.6.2/aarch64-unknown-linux-gnu":1,"flamegraph/0.6.2/aarch64-unknown-linux-musl":1,"flamegraph/0.6.2/x86_64-unknown-linux-gnu":10,"flamegraph/0.6.2/x86_64-unknown-linux-musl":10,"git-delta/0.15.1/x86_64-unknown-linux-gnu":2,"git-delta/0.15.1/x86_64-unknown-linux-musl":2,"gitoxide/0.19.0/aarch64-apple-darwin":2,"gitoxide/0.19.0/x86_64-pc-windows-msvc":3,"gitoxide/0.19.0/x86_64-unknown-linux-gnu":2,"gitoxide/0.19.0/x86_64-unknown-linux-musl":1,"gping/1.6.0/x86_64-unknown-linux-gnu":1,"gping/1.6.0/x86_64-unknown-linux-musl":1,"gping/1.6.1/aarch64-apple-darwin":1,"gping/1.6.1/x86_64-apple-darwin":1,"grcov/0.8.13/x86_64-unknown-linux-gnu":29,"grcov/0.8.13/x86_64-unknown-linux-musl":20,"igrep/0.5.1/x86_64-unknown-linux-gnu":1,"igrep/0.5.1/x86_64-unknown-linux-musl":1,"just/1.9.0/x86_64-apple-darwin":83,"just/1.9.0/x86_64-pc-windows-msvc":13,"just/1.9.0/x86_64-unknown-linux-gnu":121,"just/1.9.0/x86_64-unknown-linux-musl":121,"kani-verifier/0.17.0/aarch64-apple-darwin":1,"kani-verifier/0.17.0/x86_64-apple-darwin":1,"knope/0.4.1/x86_64-unknown-linux-gnu":5,"knope/0.4.1/x86_64-unknown-linux-musl":5,"libreddit/0.25.1/x86_64-unknown-linux-gnu":1,"libreddit/0.25.1/x86_64-unknown-linux-musl":1,"mcfly/0.7.0/x86_64-unknown-linux-gnu":1,"mcfly/0.7.0/x86_64-unknown-linux-musl":1,"mdbook-admonish/1.8.0/x86_64-unknown-linux-gnu":1,"mdbook-admonish/1.8.0/x86_64-unknown-linux-musl":1,"mdbook-kroki-preprocessor/0.1.2/x86_64-unknown-linux-gnu":1,"mdbook-kroki-preprocessor/0.1.2/x86_64-unknown-linux-musl":1,"mdbook-linkcheck/0.7.7/x86_64-unknown-linux-gnu":35,"mdbook-open-on-gh/2.3.0/x86_64-unknown-linux-gnu":1,"mdbook-open-on-gh/2.3.0/x86_64-unknown-linux-musl":1,"mdbook-regex/0.0.2/x86_64-unknown-linux-gnu":1,"mdbook-regex/0.0.2/x86_64-unknown-linux-musl":1,"mdbook/0.4.22/x86_64-unknown-linux-gnu":43,"mdbook/0.4.22/x86_64-unknown-linux-musl":8,"mdcat/0.30.3/x86_64-unknown-linux-gnu":1,"mdcat/0.30.3/x86_64-unknown-linux-musl":1,"neovim-ctrl/0.1.1/x86_64-unknown-linux-gnu":1,"neovim-ctrl/0.1.1/x86_64-unknown-linux-musl":1,"nu/0.72.0/x86_64-unknown-linux-gnu":1,"paru/1.11.0/x86_64-unknown-linux-gnu":2,"paru/1.11.0/x86_64-unknown-linux-musl":2,"pomsky-bin/0.8.0/x86_64-pc-windows-msvc":1,"pueue/3.0.0/x86_64-unknown-linux-gnu":2,"pueue/3.0.0/x86_64-unknown-linux-musl":2,"recursive_scraper/0.6.0/aarch64-apple-darwin":1,"recursive_scraper/0.6.0/x86_64-apple-darwin":1,"release-plz/0.2.26/x86_64-apple-darwin":1,"ripgrep/13.0.0/x86_64-unknown-linux-gnu":1,"ripgrep/13.0.0/x86_64-unknown-linux-musl":1,"rust-script/0.22.0/x86_64-pc-windows-msvc":1,"safecloset/0.7.0/x86_64-unknown-linux-gnu":1,"safecloset/0.7.0/x86_64-unknown-linux-musl":1,"sarif-fmt/0.3.4/x86_64-unknown-linux-gnu":5,"sarif-fmt/0.3.4/x86_64-unknown-linux-musl":5,"sccache/0.3.3/x86_64-unknown-linux-gnu":6,"sccache/0.3.3/x86_64-unknown-linux-musl":4,"sheldon/0.7.1/x86_64-unknown-linux-gnu":2,"sheldon/0.7.1/x86_64-unknown-linux-musl":2,"sic/0.20.1/aarch64-apple-darwin":1,"sic/0.20.1/x86_64-apple-darwin":1,"sqlx-cli/0.6.2/x86_64-unknown-linux-gnu":2,"sqlx-cli/0.6.2/x86_64-unknown-linux-musl":2,"starship/1.12.0/aarch64-apple-darwin":1,"starship/1.12.0/x86_64-apple-darwin":3,"starship/1.12.0/x86_64-pc-windows-msvc":1,"starship/1.12.0/x86_64-unknown-linux-gnu":7,"starship/1.12.0/x86_64-unknown-linux-musl":7,"tantivy-cli/0.19.0/x86_64-apple-darwin":1,"taplo-cli/0.8.0/x86_64-unknown-linux-gnu":38,"taplo-cli/0.8.0/x86_64-unknown-linux-musl":1,"tarpaulin/0.1.0/x86_64-unknown-linux-gnu":1,"tauri-cli/1.2.2/x86_64-apple-darwin":5,"tauri-cli/1.2.2/x86_64-pc-windows-msvc":4,"tealdeer/1.6.1/x86_64-unknown-linux-gnu":1,"tealdeer/1.6.1/x86_64-unknown-linux-musl":1,"topgrade/10.2.2/aarch64-unknown-linux-gnu":1,"topgrade/10.2.2/aarch64-unknown-linux-musl":1,"topgrade/10.2.2/x86_64-unknown-linux-gnu":1,"topgrade/10.2.2/x86_64-unknown-linux-musl":1,"wasm-bindgen-cli/0.2.83/x86_64-unknown-linux-gnu":21,"wasm-bindgen-cli/0.2.83/x86_64-unknown-linux-musl":21,"wasm-pack/0.10.3/x86_64-unknown-linux-gnu":5,"wasm-pack/0.10.3/x86_64-unknown-linux-musl":1,"whatyoumean/3.1.0/aarch64-apple-darwin":1,"whatyoumean/3.1.0/x86_64-apple-darwin":1,"xargo/0.3.26/x86_64-unknown-linux-gnu":4,"ymlfxr/0.3.2/x86_64-unknown-linux-gnu":1,"ymlfxr/0.3.2/x86_64-unknown-linux-musl":1,"zbus_xmlgen/3.1.0/x86_64-unknown-linux-gnu":1,"zbus_xmlgen/3.1.0/x86_64-unknown-linux-musl":1,"zellij/0.34.4/aarch64-apple-darwin":2,"zellij/0.34.4/aarch64-unknown-linux-gnu":2,"zellij/0.34.4/aarch64-unknown-linux-musl":2,"zellij/0.34.4/armv7-unknown-linux-gnueabihf":1,"zellij/0.34.4/armv7-unknown-linux-musleabihf":1,"zellij/0.34.4/x86_64-apple-darwin":3,"zellij/0.34.4/x86_64-unknown-linux-gnu":5,"zellij/0.34.4/x86_64-unknown-linux-musl":5,"zoxide/0.8.3/x86_64-unknown-linux-gnu":1,"zoxide/0.8.3/x86_64-unknown-linux-musl":1}
